{"files":[{"patch":"@@ -279,2 +279,4 @@\n-  Log(interpreter, oopmap) logv;\n-  LogStream st(logv.trace());\n+  typedef LogTargetImpl<LogLevel::Trace, LOG_TAGS(interpreter, oopmap) > log_type;\n+  bool const is_log_enabled = log_type::is_enabled();\n+  static const log_type log;\n+  LogStream st(log);\n@@ -282,1 +284,1 @@\n-  st.print(\"Locals (%d): \", max_locals);\n+  if (is_log_enabled) st.print(\"Locals (%d): \", max_locals);\n@@ -287,1 +289,1 @@\n-    st.print(\"%d\", v1 ? 1 : 0);\n+    if (is_log_enabled) st.print(\"%d\", v1 ? 1 : 0);\n@@ -289,1 +291,1 @@\n-  st.cr();\n+  if (is_log_enabled) st.cr();\n@@ -291,1 +293,1 @@\n-  st.print(\"Stack (%d): \", stack_top);\n+  if (is_log_enabled) st.print(\"Stack (%d): \", stack_top);\n@@ -296,1 +298,1 @@\n-    st.print(\"%d\", v1 ? 1 : 0);\n+    if (is_log_enabled) st.print(\"%d\", v1 ? 1 : 0);\n@@ -298,1 +300,1 @@\n-  st.cr();\n+  if (is_log_enabled) st.cr();\n","filename":"src\/hotspot\/share\/interpreter\/oopMapCache.cpp","additions":10,"deletions":8,"binary":false,"changes":18,"status":"modified"}]}