[{"commit":{"message":"Apply @franz1981's idea but directly to Arrays.copyOfRange, factoring out range checks and helping JIT pick the best arraycopy adapter"},"files":[{"filename":"src\/java.base\/share\/classes\/java\/util\/Arrays.java"}],"sha":"72138930fdbfe51d3a0f3d4c6b2f743590cc7e77"},{"commit":{"message":"Back out all changes except micro"},"files":[{"filename":"src\/java.base\/share\/classes\/java\/lang\/String.java"},{"filename":"src\/java.base\/share\/classes\/java\/lang\/StringLatin1.java"},{"filename":"src\/java.base\/share\/classes\/java\/lang\/StringUTF16.java"}],"sha":"4310a4f5f7d36b11c70c9ccc557623e97734d01b"}]