{"files":[{"patch":"@@ -69,1 +69,2 @@\n-            throw new SkippedException(\"You have only one monitor in your system - test skipped\");\n+            throw new SkippedException(\"You have only one monitor in your system\" +\n+                                       \" - test skipped\");\n@@ -225,1 +226,2 @@\n-            d.setLocation(new Point((int) (gc.getBounds().getX() + 20), (int) (gc.getBounds().getY() + 20)));\n+            d.setLocation(new Point((int) (gc.getBounds().getX() + 20)\n+                          , (int) (gc.getBounds().getY() + 20)));\n@@ -232,2 +234,3 @@\n-            return \"Screen \" + num + (frameOwned ? \" Frame-owned\" : \" Dialog-owned\") + (modal ? \" modal \" : \" non-modal \") +\n-                    (swing ? \"JDialog\" : \"Dialog\");\n+            return \"Screen \" + num + (frameOwned ? \" Frame-owned\" : \" Dialog-owned\")\n+                    + (modal ? \" modal \" : \" non-modal \")\n+                    + (swing ? \"JDialog\" : \"Dialog\");\n","filename":"test\/jdk\/java\/awt\/Multiscreen\/DialogTest.java","additions":7,"deletions":4,"binary":false,"changes":11,"status":"modified"},{"patch":"@@ -57,1 +57,2 @@\n-            throw new SkippedException(\"You have only one monitor in your system - test skipped\");\n+            throw new SkippedException(\"You have only one monitor in your system\" +\n+                                       \" - test skipped\");\n","filename":"test\/jdk\/java\/awt\/Multiscreen\/FillThisScreen.java","additions":2,"deletions":1,"binary":false,"changes":3,"status":"modified"},{"patch":"@@ -52,1 +52,2 @@\n-        GraphicsDevice[] gds = GraphicsEnvironment.getLocalGraphicsEnvironment().getScreenDevices();\n+        GraphicsDevice[] gds = GraphicsEnvironment.getLocalGraphicsEnvironment()\n+                               .getScreenDevices();\n@@ -54,1 +55,2 @@\n-            throw new SkippedException(\"You have only one monitor in your system - test skipped\");\n+            throw new SkippedException(\"You have only one monitor in your system\" +\n+                                       \" - test skipped\");\n","filename":"test\/jdk\/java\/awt\/Multiscreen\/IMCandidateWindowTest.java","additions":4,"deletions":2,"binary":false,"changes":6,"status":"modified"}]}