{"files":[{"patch":"@@ -76,2 +76,0 @@\n-\/\/ The implementation of integer registers for the ia32 architecture\n-\n@@ -171,1 +169,1 @@\n-  int   encoding() const                          { assert(is_valid(), \"invalid register (%d)\", (int)raw_encoding() ); return raw_encoding(); }\n+  int   encoding() const                         { assert(is_valid(), \"invalid register\"); return raw_encoding(); }\n","filename":"src\/hotspot\/cpu\/x86\/register_x86.hpp","additions":1,"deletions":3,"binary":false,"changes":4,"status":"modified"}]}