[{"commit":{"message":"Extensible API for JfrEpochQueue"},"files":[{"filename":"src\/hotspot\/share\/jfr\/recorder\/checkpoint\/types\/traceid\/jfrTraceIdKlassQueue.cpp"},{"filename":"src\/hotspot\/share\/jfr\/utilities\/jfrEpochQueue.hpp"},{"filename":"src\/hotspot\/share\/jfr\/utilities\/jfrEpochQueue.inline.hpp"}],"sha":"fc3dbb614e2bf2c2be801bb013e48e3546fb5966"},{"commit":{"message":"Merge branch '8274298' of github.com:mgronlun\/jdk into 8274298"},"files":[],"sha":"1a383904caf587f9cef6e01f719e917bd297cc8b"},{"commit":{"message":"newline"},"files":[],"sha":"8b31f3a93a47929ed61553eec2e6ada194e60d06"},{"commit":{"message":"no malloc by JfrThreadSampler"},"files":[],"sha":"1333a38ac187ac3c82a327f0e9c7ed7dabb17cde"},{"commit":{"message":"newline"},"files":[],"sha":"e43b1466b06981b7d2c8eeed47bc6f2c1025a6b3"},{"commit":{"message":"no malloc by JfrThreadSampler"},"files":[{"filename":"src\/hotspot\/share\/jfr\/recorder\/checkpoint\/types\/traceid\/jfrTraceIdKlassQueue.cpp"},{"filename":"src\/hotspot\/share\/jfr\/utilities\/jfrEpochQueue.hpp"},{"filename":"src\/hotspot\/share\/jfr\/utilities\/jfrEpochQueue.inline.hpp"}],"sha":"a4956a1f0d5399938fc02234ad50d3b924119d88"}]