[{"commit":{"message":"JavaDoc updates"},"files":[{"filename":"modules\/javafx.base\/src\/main\/java\/javafx\/collections\/transformation\/TransformationList.java"}],"sha":"b86cdfe89510aa4f1775cfc3825576e769e464c5"},{"commit":{"message":"TransformationList.getSourceIndex\/getViewIndex should throw IOOBE"},"files":[{"filename":"modules\/javafx.base\/src\/main\/java\/javafx\/collections\/transformation\/FilteredList.java"},{"filename":"modules\/javafx.base\/src\/main\/java\/javafx\/collections\/transformation\/SortedList.java"},{"filename":"modules\/javafx.base\/src\/main\/java\/javafx\/collections\/transformation\/TransformationList.java"}],"sha":"df510c22321913f8135e961086c2904f0e77a39b"},{"commit":{"message":"Add failing test"},"files":[{"filename":"modules\/javafx.base\/src\/test\/java\/test\/javafx\/collections\/FilteredListTest.java"},{"filename":"modules\/javafx.base\/src\/test\/java\/test\/javafx\/collections\/SortedListTest.java"}],"sha":"72064c0c8c5407750ba622cf8c41aaf27ab6bd2d"}]