{"files":[{"patch":"@@ -354,1 +354,1 @@\n-        var orgsToSearch = orgs.stream().map(o -> \"org:\" + o).collect(Collectors.joining(\"+\"));\n+        var orgsToSearch = orgs.stream().map(o -> \"org:\" + o).collect(Collectors.joining(\" \"));\n@@ -356,1 +356,1 @@\n-            orgsToSearch = \"+\" + orgsToSearch;\n+            orgsToSearch = \" \" + orgsToSearch;\n@@ -363,3 +363,8 @@\n-        var first = items.get(0);\n-        var repo = repository(first.get(\"repository\").get(\"full_name\").asString());\n-        return repo.get().commit(hash);\n+        \/\/ When searching for a commit, there may be hits in multiple repositories.\n+        \/\/ There is no good way of knowing for sure which repository we would rather\n+        \/\/ get the commit from, but a reasonable default is to go by the shortest\n+        \/\/ name as that is most likely the main repository of the project.\n+        var shortestName = items.stream()\n+                .map(o -> o.get(\"repository\").get(\"full_name\").asString())\n+                .min(Comparator.comparing(String::length));\n+        return shortestName.flatMap(this::repository).flatMap(r -> r.commit(hash));\n","filename":"forge\/src\/main\/java\/org\/openjdk\/skara\/forge\/github\/GitHubHost.java","additions":10,"deletions":5,"binary":false,"changes":15,"status":"modified"},{"patch":"@@ -235,0 +235,5 @@\n+                                  \/\/ When searching for a commit, there may be hits in multiple repositories.\n+                                  \/\/ There is no good way of knowing for sure which repository we would rather\n+                                  \/\/ get the commit from, but a reasonable default is to go by the shortest\n+                                  \/\/ path name as that is most likely the main repository of the project.\n+                                  .sorted(Comparator.comparing(o -> o.get(\"path\").asString().length()))\n","filename":"forge\/src\/main\/java\/org\/openjdk\/skara\/forge\/gitlab\/GitLabHost.java","additions":5,"deletions":0,"binary":false,"changes":5,"status":"modified"}]}